dune_rivals.py
dune_rivals-0.5.12.dist-info/METADATA
dune_rivals-0.5.12.dist-info/WHEEL
dune_rivals-0.5.12.dist-info/top_level.txt
dune_rivals-0.5.12.dist-info/RECORD
